README.md
overdrive.py
setup.cfg
setup.py
anki_overdrive.egg-info/PKG-INFO
anki_overdrive.egg-info/SOURCES.txt
anki_overdrive.egg-info/dependency_links.txt
anki_overdrive.egg-info/not-zip-safe
anki_overdrive.egg-info/requires.txt
anki_overdrive.egg-info/top_level.txt